nex/__init__.py
nexlang-1.3.3.dist-info/METADATA
nexlang-1.3.3.dist-info/WHEEL
nexlang-1.3.3.dist-info/top_level.txt
nexlang-1.3.3.dist-info/RECORD
