Metadata-Version: 2.4
Name: NexLang
Version: 1.3.3
Summary: Super obfuscation Library
Author: D
Author-email: nasr2python@gmail.com
Classifier: Programming Language :: Python :: 3
Classifier: Programming Language :: Python :: 3.11
Classifier: License :: OSI Approved :: MIT License
Classifier: Operating System :: OS Independent
Dynamic: author
Dynamic: author-email
Dynamic: classifier
Dynamic: description
Dynamic: description-content-type
Dynamic: summary
